flor/__init__.py
flor/constants.py
flor/flags.py
flor/iterator.py
flor/kits.py
flor/state.py
flor/hlast/__init__.py
flor/hlast/gtpropagate.py
flor/hlast/visitors.py
flor/hlast/gumtree/__init__.py
flor/hlast/gumtree/adapter.py
flor/hlast/gumtree/idmap.py
flor/hlast/gumtree/priorityq.py
flor/hlast/gumtree/python.py
flor/hlast/gumtree/test.py
flor/hlast/gumtree/tree.py
flor/journal/__init__.py
flor/journal/entry/__init__.py
flor/journal/entry/abstract.py
flor/journal/entry/constants.py
flor/journal/entry/data/__init__.py
flor/journal/entry/data/abstract.py
flor/journal/entry/data/dataframe.py
flor/journal/entry/data/reference.py
flor/journal/entry/data/torch_chkpt.py
flor/journal/entry/data/value.py
flor/journal/entry/metadata/__init__.py
flor/journal/entry/metadata/abstract.py
flor/journal/entry/metadata/bracket.py
flor/journal/entry/metadata/eof.py
flor/journal/tree/__init__.py
flor/journal/tree/block.py
flor/journal/tree/group.py
flor/journal/tree/tree.py
flor/journal/tree/window.py
flor/logger/__init__.py
flor/logger/checkpoint_logger.py
flor/logger/csv.py
flor/logger/exp_json.py
flor/logger/future.py
flor/logger/log_records.py
flor/query/__init__.py
flor/query/database.py
flor/query/pivot.py
flor/query/unpack.py
flor/shelf/__init__.py
flor/shelf/cwd_shelf.py
flor/shelf/home_shelf.py
flor/skipblock/__init__.py
flor/skipblock/abstract.py
flor/skipblock/readblock.py
flor/skipblock/seemblock.py
flor/skipblock/writeblock.py
pyflor-2.5.6.dist-info/LICENSE
pyflor-2.5.6.dist-info/METADATA
pyflor-2.5.6.dist-info/WHEEL
pyflor-2.5.6.dist-info/top_level.txt
pyflor-2.5.6.dist-info/RECORD
