Metadata-Version: 2.1
Name: pyflor
Version: 2.5.6
Summary: Fast Low-Overhead Recovery
Home-page: https://github.com/ucbrise/flor
Author: Rolando Garcia
Author-email: rogarcia@berkeley.edu
Classifier: Programming Language :: Python :: 3
Classifier: License :: OSI Approved :: Apache Software License
Classifier: Operating System :: OS Independent
Requires-Python: >=3.9
License-File: LICENSE
Requires-Dist: GitPython
Requires-Dist: cloudpickle
Requires-Dist: astunparse
Requires-Dist: pandas
Requires-Dist: bidict
